data_processing/__init__.py
data_processing/data_access/__init__.py
data_processing/data_access/arrow_s3.py
data_processing/data_access/data_access.py
data_processing/data_access/data_access_factory.py
data_processing/data_access/data_access_factory_base.py
data_processing/data_access/data_access_local.py
data_processing/data_access/data_access_s3.py
data_processing/ray/__init__.py
data_processing/ray/ray_utils.py
data_processing/ray/transform_launcher.py
data_processing/ray/transform_orchestrator.py
data_processing/ray/transform_orchestrator_configuration.py
data_processing/ray/transform_runtime.py
data_processing/ray/transform_statistics.py
data_processing/ray/transform_table_processor.py
data_processing/test_support/__init__.py
data_processing/test_support/abstract_test.py
data_processing/test_support/data_access/__init__.py
data_processing/test_support/data_access/data_access_factory_test.py
data_processing/test_support/ray/__init__.py
data_processing/test_support/ray/transform_test.py
data_processing/test_support/transform/__init__.py
data_processing/test_support/transform/noop_transform.py
data_processing/test_support/transform/transform_test.py
data_processing/transform/__init__.py
data_processing/transform/table_transform.py
data_processing/utils/__init__.py
data_processing/utils/cli_utils.py
data_processing/utils/config.py
data_processing/utils/log.py
data_processing/utils/params_utils.py
data_processing/utils/transform_utils.py
data_prep_lab-0.1.6.dist-info/METADATA
data_prep_lab-0.1.6.dist-info/WHEEL
data_prep_lab-0.1.6.dist-info/top_level.txt
data_prep_lab-0.1.6.dist-info/RECORD
