Metadata-Version: 2.1
Name: data_prep_lab
Version: 0.1.6
Summary: Data Preparation Laboratory Library
Author-email: David Wood <dawood@us.ibm.com>, Boris Lublinsky <blublinsky@ibm.com>
License: Apache-2.0
Requires-Python: >=3.10
Requires-Dist: ray[default] ==2.9.3
Requires-Dist: pyarrow ==15.0.2
Requires-Dist: boto3 ==1.34.69
Requires-Dist: argparse
Requires-Dist: mmh3
Requires-Dist: fastapi >=0.109.1
Requires-Dist: pillow >=10.2.0
Provides-Extra: dev
Requires-Dist: twine ; extra == 'dev'
Requires-Dist: pytest >=7.3.2 ; extra == 'dev'
Requires-Dist: pytest-dotenv >=0.5.2 ; extra == 'dev'
Requires-Dist: pytest-env >=1.0.0 ; extra == 'dev'
Requires-Dist: pre-commit >=3.3.2 ; extra == 'dev'
Requires-Dist: pytest-cov >=4.1.0 ; extra == 'dev'
Requires-Dist: pytest-mock >=3.10.0 ; extra == 'dev'
Requires-Dist: moto ==5.0.5 ; extra == 'dev'
Requires-Dist: markupsafe ==2.0.1 ; extra == 'dev'
